chzzk/__init__.py
chzzk/chzzk.py
chzzk/chzzk_chat.py
chzzk/client/__init__.py
chzzk/client/client.py
chzzk/client/credential.py
chzzk/client/socket.py
chzzk/core/__init__.py
chzzk/core/chzzk_channel.py
chzzk/core/chzzk_live.py
chzzk/core/chzzk_serach.py
chzzk/core/chzzk_video.py
chzzk/core/game_chat.py
chzzk/core/game_user.py
chzzk/event/__init__.py
chzzk/event/event_manager.py
chzzk/event/event_parser.py
chzzk/exception/__init__.py
chzzk/exception/chzzk_exception.py
chzzk/exception/socket_exception.py
chzzk/model/__init__.py
chzzk/model/channel.py
chzzk/model/chat.py
chzzk/model/chatmeta.py
chzzk/model/donation.py
chzzk/model/live.py
chzzk/model/message.py
chzzk/model/model.py
chzzk/model/profile.py
chzzk/model/search.py
chzzk/model/user.py
chzzk/model/video.py
chzzk/utils/__init__.py
chzzk/utils/kst.py
chzzk_sdk-0.1.3.dist-info/LICENSE
chzzk_sdk-0.1.3.dist-info/METADATA
chzzk_sdk-0.1.3.dist-info/WHEEL
chzzk_sdk-0.1.3.dist-info/top_level.txt
chzzk_sdk-0.1.3.dist-info/RECORD
