Metadata-Version: 2.1
Name: chzzk-sdk
Version: 0.1.3
Summary: An unofficial Python SDK Library for CHZZK
Home-page: https://github.com/saebyeok0306/chzzk-sdk
Author: saebyeok0306
Author-email: sehun0306.dev@gmail.com
Classifier: Programming Language :: Python :: 3
Classifier: License :: OSI Approved :: MIT License
Classifier: Operating System :: OS Independent
Requires-Python: >=3.11.7
License-File: LICENSE
Requires-Dist: pydantic
Requires-Dist: httpx
Requires-Dist: websockets
Requires-Dist: python-dotenv
Requires-Dist: mypy
